{
	"São José dos Pinhais / PR": [
		"FFA_Erico Leandro Rosa",
		"FFA_João Claudio Rodrigues",
		"FFA_Diego dos Santos",
		"OSP_Paulo Henrique Fonseca Oliveira"
	],
	"Araucária / PR":[
		"FFA_Leandro Jose Lima de Oliveira"
	],
	"Curitiba / PR":[
		"FFA_Erico Leandro Rosa",
		"FFA_Deividy Ferreira do Amaral",
		"OSP_Paulo Henrique Fonseca Oliveira"
	],
	"Lapa / PR":[
		"FFA_Deividy Ferreira do Amaral",
		"FFA_Renato Pedroso da Costa",
		"Rodrigo Santos"
	],
	"Campo Largo / PR":[
		"FFA_Leandro josé Lima de Oliveira",
		"FFA_Renato Pedroso da Costa"
	],
	"Balsa Nova / PR":[
		"FFA_Leandro josé Lima de Oliveira"
	],
	"Piraquara / PR":[
		"FFA_João Claudio Rodrigues"
	],
	"Matinhos / PR":[
		"CTS_Andre Luiz dos Santos Rabelo",
		"CTS_Maciel Laurentino da Silva",
		"CTS_Paulo Cesar da Silva",
		"CTS_Fabio Franca",
		"CTS_Alysson dos Anjos Soares"
	],
	"Antonina / PR":[
		"CTS_Cleverson José Ramos Costa",
		"CTS_Marcelo Fabiano da Silva Ferreira Barros Junior"
	],
	"Paranaguá / PR":[
		"CTS_Gabriel Henrique Pereira",
		"Allan Diensen Ezequiel de Oliveira",
		"CTS_Marcelo Franca",
		"CTS_Robson Geraldo Avelino",
		"CTS_Jhonatan Amadeu Batista",
		"CTS_Odair Cordeiro Alves Junior",
		"CTS_Alison Andrei Cristo"
	],
	"Ilha dos Valadares / PR":[
		"CTS_Jhonatan Amadeu Batista",
		"CTS_Odair Cordeiro Alves Junior"
	],
	"Alexandra / PR":[
		"CTS_Alison Andrei Cristo"
	],
	"Guaíra / SP":[
		"William Santos Delefrate"
	],
	"Campo de Santana / PR":[
		"FFA_Alisson Bibiano da Silva"
	],
	"Sorriso / MT":[
		"Vanderson Brombrilla",
		"Renato Abrao de Sousa"
	],
	"Sinop / MT":[
		"Pedro Murilo Antunes"
	],
	"Santo Antônio da Platina / PR":["Felix Antonio Pereira"],
	"Jacarezinho / PR":["Felix Antonio Pereira"],
	"Bandeirantes / PR":["Felix Antonio Pereira"],
	"Matelândia / PR":["Felix Antonio Pereira"],
	"Ponta Grossa / PR":[
		"Robson Fernando Ferreira de Mello",
		"Rogério Gonçalves"
	],
	"Medianeira / PR":["Enviar para a supervisora"],
	"Foz do Iguaçú / PR":["Enviar para a supervisora"]
}